dupimg/__init__.py
dupimg/__main__.py
dupimg/cli.py
img_phash_tools-0.0.2.dist-info/licenses/LICENSE
imgphash/__init__.py
imgphash/__main__.py
imgphash/cli.py
imgphash/image_phash.py
qsimg/__init__.py
qsimg/__main__.py
qsimg/cli.py
simg/__init__.py
simg/__main__.py
simg/cli.py
img_phash_tools-0.0.2.dist-info/METADATA
img_phash_tools-0.0.2.dist-info/WHEEL
img_phash_tools-0.0.2.dist-info/entry_points.txt
img_phash_tools-0.0.2.dist-info/top_level.txt
img_phash_tools-0.0.2.dist-info/RECORD
